.gitignore
CHANGES.txt
MANIFEST.in
README.rst
bootstrap.py
buildout.cfg
setup.py
collective/__init__.py
collective.js.jquerymobile.egg-info/PKG-INFO
collective.js.jquerymobile.egg-info/SOURCES.txt
collective.js.jquerymobile.egg-info/dependency_links.txt
collective.js.jquerymobile.egg-info/entry_points.txt
collective.js.jquerymobile.egg-info/namespace_packages.txt
collective.js.jquerymobile.egg-info/not-zip-safe
collective.js.jquerymobile.egg-info/requires.txt
collective.js.jquerymobile.egg-info/top_level.txt
collective/js/__init__.py
collective/js/jquerymobile/__init__.py
collective/js/jquerymobile/configure.zcml
collective/js/jquerymobile/interfaces.py
collective/js/jquerymobile/tests.py
collective/js/jquerymobile/example/__init__.py
collective/js/jquerymobile/example/configure.zcml
collective/js/jquerymobile/example/mobile.pt
collective/js/jquerymobile/example/mobile.py
collective/js/jquerymobile/resources/jquery.mobile.css
collective/js/jquerymobile/resources/jquery.mobile.js
collective/js/jquerymobile/resources/jquery.mobile.structure.css
collective/js/jquerymobile/resources/images/ajax-loader.gif
collective/js/jquerymobile/resources/images/icons-18-black.png
collective/js/jquerymobile/resources/images/icons-18-white.png
collective/js/jquerymobile/resources/images/icons-36-black.png
collective/js/jquerymobile/resources/images/icons-36-white.png
docs/INSTALL.txt
docs/LICENSE.txt